irnt/__init__.py
irnt/client.py
pyirnt-0.0.2.dev1.dist-info/AUTHORS
pyirnt-0.0.2.dev1.dist-info/LICENSE
pyirnt-0.0.2.dev1.dist-info/METADATA
pyirnt-0.0.2.dev1.dist-info/WHEEL
pyirnt-0.0.2.dev1.dist-info/top_level.txt
pyirnt-0.0.2.dev1.dist-info/RECORD
