Metadata-Version: 2.1
Name: pyirnt
Version: 0.0.2.dev1
Summary: A client library to facilitate fetching garbage disposal schedules from ir.nt.no
Home-page: https://github.com/bendikrb/pyirnt
Author: bendikrb
License: MIT
Project-URL: Bug Tracker, https://github.com/bendikrb/pyirnt/issues
Project-URL: Source Code, https://github.com/bendikrb/pyirnt
Keywords: api-client,unofficial
Platform: UNKNOWN
Classifier: Development Status :: 4 - Beta
Classifier: Environment :: Console
Classifier: Intended Audience :: Developers
Classifier: Programming Language :: Python :: 3
Classifier: Programming Language :: Python :: 3.6
Classifier: Programming Language :: Python :: 3.7
Classifier: Programming Language :: Python :: 3.8
Requires-Python: >= 3.6
License-File: LICENSE
License-File: AUTHORS
Requires-Dist: urllib3
Requires-Dist: requests (~=2.26.0)
Requires-Dist: setuptools (~=58.5.3)
Requires-Dist: beautifulsoup4 (~=4.10.0)
